{
    "os": "Linux-6.2.0-36-generic-x86_64-with-glibc2.17",
    "python": "3.8.10",
    "heartbeatAt": "2024-01-22T15:30:42.530668",
    "startedAt": "2024-01-22T15:30:41.813698",
    "docker": null,
    "cuda": null,
    "args": [
        "--env",
        "coin3",
        "--num-agents",
        "3",
        "--rollout-len",
        "1000",
        "--user_name",
        "1160677229"
    ],
    "state": "running",
    "program": "run_scripts/sb3_train.py",
    "codePathLocal": "run_scripts/sb3_train.py",
    "codePath": "run_scripts/sb3_train.py",
    "git": {
        "remote": "https://github.com/stevenqing/ssd.git",
        "commit": "0a3ecffb4459ea9a003bf942074feb4758a0b346"
    },
    "email": null,
    "root": "/home/shuqingshi/Downloads/ssd",
    "host": "nmslap007078",
    "username": "shuqingshi",
    "executable": "/home/shuqingshi/miniconda3/envs/melting-ssd/bin/python",
    "cpu_count": 10,
    "cpu_count_logical": 12,
    "cpu_freq": {
        "current": 1638.270166666667,
        "min": 400.0,
        "max": 4333.333333333333
    },
    "cpu_freq_per_core": [
        {
            "current": 510.706,
            "min": 400.0,
            "max": 5200.0
        },
        {
            "current": 1387.357,
            "min": 400.0,
            "max": 5200.0
        },
        {
            "current": 1699.995,
            "min": 400.0,
            "max": 5200.0
        },
        {
            "current": 2700.0,
            "min": 400.0,
            "max": 5200.0
        },
        {
            "current": 1700.014,
            "min": 400.0,
            "max": 3900.0
        },
        {
            "current": 1700.202,
            "min": 400.0,
            "max": 3900.0
        },
        {
            "current": 2700.0,
            "min": 400.0,
            "max": 3900.0
        },
        {
            "current": 1700.054,
            "min": 400.0,
            "max": 3900.0
        },
        {
            "current": 739.097,
            "min": 400.0,
            "max": 3900.0
        },
        {
            "current": 1261.684,
            "min": 400.0,
            "max": 3900.0
        },
        {
            "current": 1365.083,
            "min": 400.0,
            "max": 3900.0
        },
        {
            "current": 398.651,
            "min": 400.0,
            "max": 3900.0
        }
    ],
    "disk": {
        "/": {
            "total": 913.7511215209961,
            "used": 53.406768798828125
        }
    },
    "memory": {
        "total": 30.937389373779297
    }
}
